modisco-2.5.2.data/scripts/modisco
modisco-2.5.2.dist-info/licenses/LICENSE
modiscolite/__init__.py
modiscolite/affinitymat.py
modiscolite/aggregator.py
modiscolite/bed_writer.py
modiscolite/cluster.py
modiscolite/core.py
modiscolite/descriptive_report.py
modiscolite/extract_seqlets.py
modiscolite/fasta_writer.py
modiscolite/gapped_kmer.py
modiscolite/io.py
modiscolite/meme_writer.py
modiscolite/report.py
modiscolite/tfmodisco.py
modiscolite/util.py
modiscolite/templates/__init__.py
modiscolite/templates/descriptive_report.html
modisco-2.5.2.dist-info/METADATA
modisco-2.5.2.dist-info/WHEEL
modisco-2.5.2.dist-info/top_level.txt
modisco-2.5.2.dist-info/RECORD
